gepard/__init__.py
gepard/adim.py
gepard/bmk.py
gepard/c1dvcs.py
gepard/c1dvmp.py
gepard/cff.py
gepard/constants.py
gepard/data.py
gepard/dis.py
gepard/dvcs.py
gepard/dvmp.py
gepard/eff.py
gepard/evolution.py
gepard/fits.py
gepard/fitter.py
gepard/gk.py
gepard/gpd.py
gepard/kinematics.py
gepard/mellin.py
gepard/model.py
gepard/plots.py
gepard/qcd.py
gepard/quadrature.py
gepard/special.py
gepard/theory.py
gepard/wilson.py
gepard/datasets/__init__.py
gepard/datasets/DIS/F2-H1-01.dat
gepard/datasets/DIS/F2-H1-02.dat
gepard/datasets/DIS/F2-H1-03.dat
gepard/datasets/DIS/F2-H1-04.dat
gepard/datasets/DIS/F2-H1-05.dat
gepard/datasets/DIS/F2-H1-06.dat
gepard/datasets/DIS/F2-H1-07.dat
gepard/datasets/DIS/F2-H1-08.dat
gepard/datasets/DIS/F2-H1-09.dat
gepard/datasets/DIS/F2-H1-10.dat
gepard/datasets/DIS/F2-H1-11.dat
gepard/datasets/DIS/F2-H1-12.dat
gepard/datasets/DIS/__init__.py
gepard/datasets/en2engamma/BSS-HALLA-20.dat
gepard/datasets/en2engamma/BSSw-HALLA-20_MC.dat
gepard/datasets/en2engamma/X-HALLA-20.dat
gepard/datasets/en2engamma/__init__.py
gepard/datasets/ep2epgamma/ALTBHDVCS-HERMES-11.dat
gepard/datasets/ep2epgamma/ALTI-HERMES-11.dat
gepard/datasets/ep2epgamma/ALUDVCS-HERMES-12.dat
gepard/datasets/ep2epgamma/ALUDVCS-HERMES-12_4bins.dat
gepard/datasets/ep2epgamma/ALUI-HERMES-12.dat
gepard/datasets/ep2epgamma/ALUI-HERMES-12_4bins.dat
gepard/datasets/ep2epgamma/AUTDVCS-HERMES-08.dat
gepard/datasets/ep2epgamma/AUTI-HERMES-08.dat
gepard/datasets/ep2epgamma/BCA-HERMES-08.dat
gepard/datasets/ep2epgamma/BCA-HERMES-09.dat
gepard/datasets/ep2epgamma/BCA-HERMES-12.dat
gepard/datasets/ep2epgamma/BCA-HERMES-12_4bins.dat
gepard/datasets/ep2epgamma/BSA-CLAS-07.dat
gepard/datasets/ep2epgamma/BSA-CLAS-07_CLAS.dat
gepard/datasets/ep2epgamma/BSA-CLAS-07_DM.dat
gepard/datasets/ep2epgamma/BSA-CLAS-07_KK.dat
gepard/datasets/ep2epgamma/BSA-CLAS-08.dat
gepard/datasets/ep2epgamma/BSA-CLAS-14.dat
gepard/datasets/ep2epgamma/BSA-CLAS-14_KK.dat
gepard/datasets/ep2epgamma/BSA-CLAS-15.dat
gepard-0.9.10.dist-info/LICENSE
gepard-0.9.10.dist-info/METADATA
gepard-0.9.10.dist-info/WHEEL
gepard-0.9.10.dist-info/top_level.txt
gepard-0.9.10.dist-info/RECORD
