Metadata-Version: 2.1
Name: gepard
Version: 0.9.10
Summary: Tool for studying the 3D quark and gluon distributions in the nucleon
Home-page: https://gepard.phy.hr
Author: Krešimir Kumerički
Author-email: kkumer@phy.hr
License: AGPL-3.0
Project-URL: Sources, https://github.com/kkumer/gepard
Project-URL: Bug Tracker, https://github.com/kkumer/gepard/issues
Project-URL: Changelog, https://github.com/kkumer/gepard/blob/master/CHANGELOG.rst
Keywords: Physics,Particle Physics
Platform: UNKNOWN
Classifier: Development Status :: 4 - Beta
Classifier: Intended Audience :: Science/Research
Classifier: License :: OSI Approved :: GNU Affero General Public License v3 or later (AGPLv3+)
Classifier: Operating System :: OS Independent
Classifier: Programming Language :: Python
Classifier: Programming Language :: Python :: 3
Classifier: Programming Language :: Python :: 3.10
Classifier: Programming Language :: Python :: Implementation :: CPython
Classifier: Topic :: Scientific/Engineering :: Physics
Requires-Python: >=3.7
License-File: LICENSE
